dns_explorer/__init__.py
dns_explorer/py.typed
dns_explorer/conf/dns_explorer.cfg
dns_explorer/conf/dns_explorer.logo
dns_explorer/conf/dns_explorer_util.cfg
dns_explorer/conf/subdomains.yaml
dns_explorer/log/dns_explorer.log
dns_explorer/pro/__init__.py
usr/local/bin/dns_explorer_run.py
dns_explorer-1.0.3.dist-info/LICENSE
dns_explorer-1.0.3.dist-info/METADATA
dns_explorer-1.0.3.dist-info/WHEEL
dns_explorer-1.0.3.dist-info/top_level.txt
dns_explorer-1.0.3.dist-info/RECORD
