Metadata-Version: 2.1
Name: dns_explorer
Version: 1.0.3
Summary: Python package for dns exploration
Home-page: https://vroncevic.github.io/dns_explorer
Author: Vladimir Roncevic
Author-email: elektron.ronca@gmail.com
License: GPL 2024 Free software to use and distributed it.
Keywords: setup,python,install,dns,explore
Platform: any
Classifier: Programming Language :: Python :: 3.10
Classifier: Programming Language :: Python :: 3.11
Classifier: License :: OSI Approved :: GNU Lesser General Public License v2 (LGPLv2)
Classifier: License :: OSI Approved :: GNU Lesser General Public License v2 or later (LGPLv2+)
Classifier: License :: OSI Approved :: GNU Lesser General Public License v3 (LGPLv3)
Classifier: License :: OSI Approved :: GNU Lesser General Public License v3 or later (LGPLv3+)
Classifier: License :: OSI Approved :: GNU Library or Lesser General Public License (LGPL)
Requires-Python: >=3.10
License-File: LICENSE
Requires-Dist: ats-utilities
Requires-Dist: dnspython
